ghstars/__init__.py
ghstars/__main__.py
ghstars/_cli.py
ghstars/_models.py
ghstars/base.html.j2
ghstars/index.html.j2
ghstars/py.typed
ghstars/stargazers.gql
ghstars/commands/__init__.py
ghstars/commands/_base.py
ghstars/commands/_fetch.py
ghstars/commands/_render.py
ghstars/commands/_top_authors.py
ghstars/commands/_top_followed.py
ghstars/commands/_version.py
ghstars-0.2.0.dist-info/entry_points.txt
ghstars-0.2.0.dist-info/LICENSE
ghstars-0.2.0.dist-info/WHEEL
ghstars-0.2.0.dist-info/METADATA
ghstars-0.2.0.dist-info/RECORD
